BISOInvest/__init__.py
BISOInvest/cli.py
BISOInvest/nordnetAPI.py
BISOInvest_data-0.1.0.dist-info/LICENSE.txt
BISOInvest_data-0.1.0.dist-info/METADATA
BISOInvest_data-0.1.0.dist-info/WHEEL
BISOInvest_data-0.1.0.dist-info/entry_points.txt
BISOInvest_data-0.1.0.dist-info/top_level.txt
BISOInvest_data-0.1.0.dist-info/RECORD
